{"abstract":{"en":"This page introduces the experiences and potential of using Artificial Intelligence (AI) and Machine Learning (ML) for classifying and coding in official statistics, specifically within the context of Work Package 10 “From Text to Code” (WP10) of the AIML4OS project. This WP aims to explore AI/ML methodologies for enhancing the accuracy and efficiency of classification and coding processes used National Statistical Institutes (NSI).","fr":"This page introduces the experiences and potential of using Artificial Intelligence (AI) and Machine Learning (ML) for classifying and coding in official statistics, specifically within the context of Work Package 10 “From Text to Code” (WP10) of the AIML4OS project. This WP aims to explore AI/ML methodologies for enhancing the accuracy and efficiency of classification and coding processes used National Statistical Institutes (NSI)."},"authors":{},"category":"training courses with R and Python","deploymentUrl":{},"imageUrl":"https://encrypted-tbn0.gstatic.com/images?q=tbn:ANd9GcQY-OenRMvFyZUfDm_snUCxpV4SyaHvUeqObA&s","lastModification":"2025-11-14","license":"CC-BY 4.0","name":{"en":"AIML4OS WP10 From text to code","fr":"AIML4OS WP10 From text to code"},"skills":{},"suggestedRequirements":["https://quarto.org/","https://scikit-learn.org/stable/"],"tags":["AI/ML","Classifying and Coding","WP10","Official Statistics"],"timeRequired":90}